vFXT/__init__.py
vFXT/aws.py
vFXT/cidr.py
vFXT/cluster.py
vFXT/gce.py
vFXT/msazure.py
vFXT/service.py
vFXT/serviceInstance.py
vFXT/version.py
vFXT/xmlrpcClt.py
vFXT-0.5.4.4.data/scripts/vfxt.py
vFXT-0.5.4.4.dist-info/DESCRIPTION.rst
vFXT-0.5.4.4.dist-info/METADATA
vFXT-0.5.4.4.dist-info/RECORD
vFXT-0.5.4.4.dist-info/WHEEL
vFXT-0.5.4.4.dist-info/metadata.json
vFXT-0.5.4.4.dist-info/top_level.txt
