Metadata-Version: 2.0
Name: vFXT
Version: 0.5.4.4
Summary: The Avere virtual FXT (vFXT) Python library and vfxt.py command line utility
Home-page: http://www.averesystems.com
Author: Jason Woodward
Author-email: woodwardj@averesystems.com
License: MIT
Platform: UNKNOWN
Classifier: Development Status :: 5 - Production/Stable
Classifier: Environment :: Console
Classifier: Intended Audience :: Developers
Classifier: Intended Audience :: System Administrators
Classifier: License :: OSI Approved :: MIT License
Classifier: Operating System :: POSIX
Classifier: Programming Language :: Python :: 2.7
Classifier: Programming Language :: Python :: 3
Requires-Dist: future
Requires-Dist: requests
Requires-Dist: boto
Requires-Dist: oauth2client
Requires-Dist: google-api-python-client
Requires-Dist: requests-oauthlib
Requires-Dist: adal (==1.2.4)
Requires-Dist: azure-cli-core (==2.10.1)
Requires-Dist: azure-common (==1.1.25)
Requires-Dist: azure-mgmt-authorization (==0.60.0)
Requires-Dist: azure-mgmt-compute (==13.0.0)
Requires-Dist: azure-identity (==1.3.1)
Requires-Dist: azure-mgmt-msi (==1.0.0)
Requires-Dist: azure-mgmt-network (==11.0.0)
Requires-Dist: azure-mgmt-resource (==10.1.0)
Requires-Dist: azure-mgmt-storage (==11.1.0)
Requires-Dist: azure-storage-blob (==12.4.0)
Requires-Dist: azure-storage-queue (==12.1.2)
Requires-Dist: azure-storage-common (==2.1.0)
Requires-Dist: knack (==0.7.2)
Requires-Dist: msrest (==0.6.18)
Requires-Dist: msrestazure (==0.6.4)
